Metadata-Version: 1.0
Name: distribution-statistics
Version: 0.1
Summary: Gaussian distributions and Binomial distributions
Home-page: UNKNOWN
Author: Javad Gholizadeh
Author-email: jgolizadeh@gmail.com
License: UNKNOWN
Platform: UNKNOWN
